{
	"ret": true,
	"recommendInfo":[{
					"id":"1",
					"link":"#",
					"src":"http://img1.qunarzz.com/sight/p0/1707/58/582f4fc547ddc880a3.img.jpg_228x168_6f125bcf.jpg",
					"name":"长隆野生动物世界",
					"level":"(5A)",
					"money":"4.5",
					"iconfont":"&#xe64b;&#xe64b;&#xe64b;&#xe64b;&#xe64b;",
					"commendNum":"30114条评论",
					"subposition":"广州·广州长隆旅游度假区"
			},{
					"id":"2",
					"link":"#",
					"src":"http://img1.qunarzz.com/sight/p0/1707/47/477416df92210439a3.img.jpg_228x168_9fb06d3e.jpg",
					"name":"长隆欢乐世界",
					"level":"(5A)",
					"money":"218.01",
					"iconfont":"&#xe64b;&#xe64b;&#xe64b;&#xe64b;&#xe64b;",
					"commendNum":"16523条评论",
					"subposition":"广州·广州长隆旅游度假区"
			},{
					"id":"3",
					"link":"#",
					"src":"http://img1.qunarzz.com/sight/p0/1603/3b/3bd311262ee06d8c90.img.jpg_228x168_566646fc.jpg",
					"name":"广州长隆旅游度假区",
					"level":"(5A)",
					"money":"4.5",
					"iconfont":"&#xe64b;&#xe64b;&#xe64b;&#xe64b;&#xe64b;",
					"commendNum":"33578条评论",
					"subposition":"广州·番禺"
			},{
					"id":"4",
					"link":"#",
					"src":"http://img1.qunarzz.com/sight/p0/1507/9e/7b5e0a44cb0310280b1aeb2a8dd94de8.water.jpg_228x168_f3806a93.jpg",
					"name":"长隆国际大马戏剧院",
					"level":"(5A)",
					"money":"346",
					"iconfont":"&#xe64b;&#xe64b;&#xe64b;&#xe64b;&#xe64b;",
					"commendNum":"30114条评论",
					"subposition":"广州·广州长隆旅游度假区"
			},{
					"id":"5",
					"link":"#",
					"src":"http://img1.qunarzz.com/sight/p0/1506/95/f4f87c47bfba5ff368bed3fb9a0b45fb.water.jpg_228x168_dda1b945.jpg",
					"name":"广州长隆酒店白虎餐厅",
					"level":"(5A)",
					"money":"198",
					"iconfont":"&#xe64b;&#xe64b;&#xe64b;&#xe64b;&#xe64b;",
					"commendNum":"304条评论",
					"subposition":"广州·广州长隆旅游度假区"
			},{
					"id":"6",
					"link":"#",
					"src":"http://img1.qunarzz.com/sight/p0/1603/ee/ee2fb567add7969390.water.jpg_228x168_94b38380.jpg",
					"name":"广州塔",
					"level":"(4A)",
					"money":"68",
					"iconfont":"&#xe64b;&#xe64b;&#xe64b;&#xe64b;&#xe64b;",
					"commendNum":"78564条评论",
					"subposition":"广州·海珠区"
			},{
					"id":"7",
					"link":"#",
					"src":"http://img1.qunarzz.com/sight/p0/1707/58/582f4fc547ddc880a3.img.jpg_228x168_6f125bcf.jpg",
					"name":"长隆野生动物世界",
					"level":"(5A)",
					"money":"56",
					"iconfont":"&#xe64b;&#xe64b;&#xe64b;&#xe64b;&#xe64b;",
					"commendNum":"30114条评论",
					"subposition":"广州·广州长隆旅游度假区"
			}],

	"qnrecommendinfo":[{
					"ticketTitle":"【暑期特惠】广州长隆水上乐园亲子票1大1小",
					"priceNum":"262",
					"ticketCost":"280"
			}],

		"ticketinfo":[{
			"id":"1",
			"title":"促销票",
			"name":"[长隆周年庆]长隆水上乐园成人票（仅限8月28日）",
			"price":"149",
			"ticketTitle":"【暑期特惠】广州长隆水上乐园亲子票1大1小",
			"priceNum":"262",
			"priceCost":"280"
		},{
			"id":"2",
			"title":"无敌票",
			"name":"[长隆周年庆]长隆水上乐园成人票（仅限8月28日）",
			"price":"149",
			"ticketTitle":"【暑期特惠】广州长隆水上乐园亲子票1大1小",
			"priceNum":"262",
			"priceCost":"280"
		},{
			"id":"3",
			"title":"特价票",
			"name":"[长隆周年庆]长隆水上乐园成人票（仅限8月28日）",
			"price":"149",
			"ticketTitle":"【暑期特惠】广州长隆水上乐园亲子票1大1小",
			"priceNum":"262",
			"priceCost":"280"
		},{
			"id":"4",
			"title":"亲子票",
			"name":"[长隆周年庆]长隆水上乐园成人票（仅限8月28日）",
			"price":"149",
			"ticketTitle":"【暑期特惠】广州长隆水上乐园亲子票1大1小",
			"priceNum":"262",
			"priceCost":"280"
		}],
	"tickethinfo":[{
			"id":"1",
			"name":"[长隆周年庆]长隆水上乐园成人票（仅限8月28日）",
			"price":"149",
			"ticketTitle":"【暑期特惠】广州长隆水上乐园亲子票1大1小",
			"priceNum":"262",
			"priceCost":"280"
		},{
			"id":"2",
			"name":"[长隆周年庆]长隆水上乐园成人票（仅限8月28日）",
			"price":"149",
			"ticketTitle":"【暑期特惠】广州长隆水上乐园亲子票1大1小",
			"priceNum":"262",
			"priceCost":"280"
		}]
}